odoo/addons/project_operating_unit/README.rst
odoo/addons/project_operating_unit/__init__.py
odoo/addons/project_operating_unit/__manifest__.py
odoo/addons/project_operating_unit/i18n/it.po
odoo/addons/project_operating_unit/i18n/project_operating_unit.pot
odoo/addons/project_operating_unit/i18n/pt.po
odoo/addons/project_operating_unit/models/__init__.py
odoo/addons/project_operating_unit/models/project_project.py
odoo/addons/project_operating_unit/models/project_task.py
odoo/addons/project_operating_unit/readme/CONTRIBUTORS.md
odoo/addons/project_operating_unit/readme/CREDITS.md
odoo/addons/project_operating_unit/readme/DESCRIPTION.md
odoo/addons/project_operating_unit/readme/USAGE.md
odoo/addons/project_operating_unit/security/project_security.xml
odoo/addons/project_operating_unit/static/description/icon.png
odoo/addons/project_operating_unit/static/description/index.html
odoo/addons/project_operating_unit/tests/__init__.py
odoo/addons/project_operating_unit/tests/test_project_operating_unit.py
odoo/addons/project_operating_unit/views/project_project.xml
odoo/addons/project_operating_unit/views/project_task.xml
odoo_addon_project_operating_unit-17.0.1.0.0.2.dist-info/METADATA
odoo_addon_project_operating_unit-17.0.1.0.0.2.dist-info/WHEEL
odoo_addon_project_operating_unit-17.0.1.0.0.2.dist-info/top_level.txt
odoo_addon_project_operating_unit-17.0.1.0.0.2.dist-info/RECORD
