Metadata-Version: 2.1
Name: odoo-addon-project_operating_unit
Version: 17.0.1.0.0.2
Requires-Python: >=3.10
Requires-Dist: odoo-addon-operating_unit>=17.0dev,<17.1dev
Requires-Dist: odoo>=17.0a,<17.1dev
Summary: This module adds operating unit information to projects and tasks.
Home-page: https://github.com/OCA/operating-unit
License: AGPL-3
Author: Open Source Integrators, Serpent Consulting Services Pvt. Ltd., Odoo Community Association (OCA)
Author-email: support@odoo-community.org
Classifier: Programming Language :: Python
Classifier: Framework :: Odoo
Classifier: Framework :: Odoo :: 17.0
Classifier: License :: OSI Approved :: GNU Affero General Public License v3
Classifier: Development Status :: 4 - Beta
